{
  "_meta": {
    "desc": "去重记录 [news]，保留 7 天",
    "updated": "2026-07-05"
  },
  "urls": {
    "o7mrki": "2026-07-05",
    "upoefw": "2026-07-05",
    "1hng21a": "2026-07-05",
    "283fin": "2026-07-05",
    "1cp1u55": "2026-07-05",
    "pabvl7": "2026-07-05",
    "2zdmu6": "2026-07-05",
    "e585k7": "2026-07-05",
    "s76vyh": "2026-07-05",
    "1ysmoob": "2026-07-05",
    "25w3lv": "2026-07-05",
    "kv8srp": "2026-07-05",
    "152swy9": "2026-07-05",
    "1julggz": "2026-07-05",
    "755f8e": "2026-07-05",
    "lw1p82": "2026-07-05",
    "1ay3scy": "2026-07-05",
    "8h6ljv": "2026-07-05",
    "p6eake": "2026-07-05",
    "f4dhba": "2026-07-05",
    "1ehi8ra": "2026-07-05",
    "zfizhp": "2026-07-05",
    "15ssf73": "2026-07-05",
    "jwj57w": "2026-07-05",
    "w67pbg": "2026-07-05",
    "pqcmj8": "2026-07-05",
    "ny0u73": "2026-07-05",
    "1owin3x": "2026-07-05",
    "gsgj66": "2026-07-05",
    "tdon9n": "2026-07-05",
    "1s4z7un": "2026-07-05",
    "kvnr2c": "2026-07-05",
    "11bn6ic": "2026-07-05",
    "1na918g": "2026-07-05",
    "1uov77f": "2026-07-05",
    "1i8tvug": "2026-07-05",
    "zjof53": "2026-07-05",
    "16dm5ka": "2026-07-05",
    "5knvlh": "2026-07-05",
    "1fw4ye7": "2026-07-05",
    "15rc0rv": "2026-07-05",
    "vpyrpd": "2026-07-05",
    "wrmcyz": "2026-07-05",
    "85npf2": "2026-07-05",
    "1lhsh10": "2026-07-05",
    "8z2t18": "2026-07-05",
    "1dj3sjw": "2026-07-05",
    "12111ht": "2026-07-05",
    "atzq81": "2026-07-05",
    "i6rirp": "2026-07-05",
    "19bvd0f": "2026-07-05",
    "13o6r70": "2026-07-05",
    "364y4x": "2026-07-05",
    "k9723j": "2026-07-05",
    "x3g5fo": "2026-07-05",
    "9y24o4": "2026-07-05",
    "17efjty": "2026-07-05",
    "19hm1ff": "2026-07-05",
    "d56cqh": "2026-07-05",
    "105c63d": "2026-07-05",
    "15hblzf": "2026-07-05",
    "1nx6t6r": "2026-07-05",
    "1ybjm6k": "2026-07-05",
    "1o1a3zr": "2026-07-05",
    "1ffsj6r": "2026-07-05",
    "hc1c1u": "2026-07-05",
    "1sv5c3k": "2026-07-05",
    "2nk4i5": "2026-07-05",
    "3lx3qj": "2026-07-05",
    "1gpbrwd": "2026-07-05",
    "umifxz": "2026-07-05",
    "1nraias": "2026-07-05",
    "1xv4iz6": "2026-07-05",
    "ddfnrv": "2026-07-05",
    "10ck6kg": "2026-07-05",
    "1bzxnqm": "2026-07-05",
    "o2if61": "2026-07-05",
    "10thb8x": "2026-07-05",
    "1ol9bdp": "2026-07-05",
    "y8hfcc": "2026-07-05",
    "d3g22w": "2026-07-05",
    "1tskldw": "2026-07-05",
    "1i4563x": "2026-07-05",
    "o5tr2l": "2026-07-05",
    "v7vmpv": "2026-07-05",
    "10832bj": "2026-07-05",
    "1ob9poq": "2026-07-05",
    "7vyoqs": "2026-07-05",
    "v6qam0": "2026-07-05",
    "f1d9xp": "2026-07-05",
    "8xbmny": "2026-07-05",
    "14gtc0x": "2026-07-05",
    "p5ta6x": "2026-07-05",
    "hj435k": "2026-07-05",
    "frudwy": "2026-07-05",
    "1e71qoa": "2026-07-05",
    "1e6n7rq": "2026-07-05"
  },
  "titles": {
    "1hoebxs": "2026-07-05",
    "1ugyyo4": "2026-07-05",
    "c559qh": "2026-07-05",
    "kovts0": "2026-07-05",
    "1p4e36p": "2026-07-05",
    "b1ro1d": "2026-07-05",
    "14qloaj": "2026-07-05",
    "10ft8r1": "2026-07-05",
    "137jhry": "2026-07-05",
    "1uo59nz": "2026-07-05",
    "1xfn3x1": "2026-07-05",
    "18sy99z": "2026-07-05",
    "1qnahhg": "2026-07-05",
    "1tnlnzq": "2026-07-05",
    "1qyrcpp": "2026-07-05",
    "z002tc": "2026-07-05",
    "jtaxpg": "2026-07-05",
    "yn6uzy": "2026-07-05",
    "6gub98": "2026-07-05",
    "tudycb": "2026-07-05",
    "cea1bg": "2026-07-05",
    "vvt0bj": "2026-07-05",
    "1q168ph": "2026-07-05",
    "1k5irvt": "2026-07-05",
    "zpkpvw": "2026-07-05",
    "1yg00b2": "2026-07-05",
    "ggralm": "2026-07-05",
    "1g9g2l9": "2026-07-05",
    "mgli3g": "2026-07-05",
    "1a63tnz": "2026-07-05",
    "1gibogg": "2026-07-05",
    "1joeoil": "2026-07-05",
    "n250hy": "2026-07-05",
    "smzhgb": "2026-07-05",
    "22g8bu": "2026-07-05",
    "4femlj": "2026-07-05",
    "i2em9n": "2026-07-05",
    "8phikv": "2026-07-05",
    "1k200dl": "2026-07-05",
    "13iwx5u": "2026-07-05",
    "1bzk3xd": "2026-07-05",
    "ackgwi": "2026-07-05",
    "a32spf": "2026-07-05",
    "ssdwsx": "2026-07-05",
    "nwe0x8": "2026-07-05",
    "10pq42f": "2026-07-05",
    "1a4txze": "2026-07-05",
    "1smhlcg": "2026-07-05",
    "mf5ikl": "2026-07-05",
    "1v5ldg1": "2026-07-05",
    "rscpyz": "2026-07-05",
    "1kcm5n5": "2026-07-05",
    "c8cby4": "2026-07-05",
    "1rajl0v": "2026-07-05",
    "1alpsop": "2026-07-05",
    "nqnm38": "2026-07-05",
    "k4a8mm": "2026-07-05",
    "jx1epn": "2026-07-05",
    "kkrksu": "2026-07-05",
    "1opdznm": "2026-07-05",
    "1pc2281": "2026-07-05",
    "1o0rhpy": "2026-07-05",
    "1r35mze": "2026-07-05",
    "1dahzgh": "2026-07-05",
    "19l7c01": "2026-07-05",
    "a6uowg": "2026-07-05",
    "2d7d68": "2026-07-05",
    "13khxh2": "2026-07-05",
    "rs46ed": "2026-07-05",
    "gl09ac": "2026-07-05",
    "1iytv7p": "2026-07-05",
    "79z5gv": "2026-07-05",
    "1x6ryie": "2026-07-05",
    "19uulx1": "2026-07-05",
    "zpllaa": "2026-07-05",
    "f5gso": "2026-07-05",
    "7qhkts": "2026-07-05",
    "1m7w7co": "2026-07-05",
    "90wpqb": "2026-07-05",
    "zhqcxu": "2026-07-05",
    "ixbn76": "2026-07-05",
    "wndz6e": "2026-07-05",
    "1fdxam4": "2026-07-05",
    "tibpm2": "2026-07-05",
    "1gdu6my": "2026-07-05",
    "w05h93": "2026-07-05",
    "hpjphy": "2026-07-05",
    "1hz82cf": "2026-07-05",
    "1jphvr8": "2026-07-05",
    "1a6d13s": "2026-07-05",
    "1ywi5up": "2026-07-05",
    "1uv0uqy": "2026-07-05",
    "10wcecz": "2026-07-05",
    "z4aqhs": "2026-07-05",
    "whyev7": "2026-07-05",
    "1xwcsco": "2026-07-05",
    "1pondb3": "2026-07-05"
  }
}
